yantu/__init__.py
yantu/api_requestor.py
yantu/yantu_object.py
yantu-1.2.dist-info/METADATA
yantu-1.2.dist-info/WHEEL
yantu-1.2.dist-info/top_level.txt
yantu-1.2.dist-info/RECORD
