Metadata-Version: 2.1
Name: yantu
Version: 1.2
Summary: Yantu tools for python
Home-page: https://gitee.com/Sea-Depth/yantu-tools-test
Author: yantu-tech
Author-email: GuoHuai Wu <wu466687121@qq.com>
License: MIT License
Keywords: python,yantu,中文,人工智能
Classifier: Intended Audience :: Developers
Classifier: Programming Language :: Python :: 3
Classifier: Operating System :: Microsoft :: Windows
Requires-Python: >=3.8
Requires-Dist: requests
Requires-Dist: setuptools
